dictdiffer/__init__.py
dictdiffer/_compat.py
dictdiffer/conflict.py
dictdiffer/merge.py
dictdiffer/resolve.py
dictdiffer/unify.py
dictdiffer/utils.py
dictdiffer/version.py
dictdiffer-0.8.0.dist-info/AUTHORS
dictdiffer-0.8.0.dist-info/LICENSE
dictdiffer-0.8.0.dist-info/METADATA
dictdiffer-0.8.0.dist-info/WHEEL
dictdiffer-0.8.0.dist-info/top_level.txt
dictdiffer-0.8.0.dist-info/RECORD
