Metadata-Version: 2.1
Name: dictdiffer
Version: 0.8.0
Summary: Dictdiffer is a library that helps you to diff and patch dictionaries.
Home-page: https://github.com/inveniosoftware/dictdiffer
Author: Invenio Collaboration
Author-email: info@inveniosoftware.org
License: UNKNOWN
Project-URL: Docs, https://dictdiffer.rtfd.io/
Project-URL: Changelog, https://github.com/inveniosoftware/dictdifferblob/master/CHANGES
Platform: UNKNOWN
Classifier: Programming Language :: Python :: 2
Classifier: Programming Language :: Python :: 2.7
Classifier: Programming Language :: Python :: 3
Classifier: Programming Language :: Python :: 3.4
Classifier: Programming Language :: Python :: 3.5
Classifier: Programming Language :: Python :: 3.6
Classifier: Programming Language :: Python :: 3.7
Classifier: Development Status :: 5 - Production/Stable
Classifier: Intended Audience :: Developers
Classifier: License :: OSI Approved :: MIT License
Classifier: Operating System :: OS Independent
Classifier: Topic :: Utilities
Provides-Extra: docs
Provides-Extra: tests
Provides-Extra: numpy
Provides-Extra: all
